salahhemdan/__init__.py
salahhemdan/downloader.py
salahhemdan-0.2.dist-info/licenses/LICENSE
salahhemdan-0.2.dist-info/METADATA
salahhemdan-0.2.dist-info/WHEEL
salahhemdan-0.2.dist-info/top_level.txt
salahhemdan-0.2.dist-info/RECORD
